[
  {
    "tag_name": "entity",
    "ids_to_tags": {
      "1": "B-app_type",
      "2": "I-app_type",
      "3": "L-app_type",
      "4": "U-app_type",
      "5": "B-confirmation",
      "6": "I-confirmation",
      "7": "L-confirmation",
      "8": "U-confirmation",
      "9": "B-downtime_tolerance",
      "10": "I-downtime_tolerance",
      "11": "L-downtime_tolerance",
      "12": "U-downtime_tolerance",
      "13": "B-feature_type",
      "14": "I-feature_type",
      "15": "L-feature_type",
      "16": "U-feature_type",
      "17": "B-relationship_type",
      "18": "I-relationship_type",
      "19": "L-relationship_type",
      "20": "U-relationship_type",
      "0": "O"
    },
    "tags_to_ids": {
      "B-app_type": 1,
      "I-app_type": 2,
      "L-app_type": 3,
      "U-app_type": 4,
      "B-confirmation": 5,
      "I-confirmation": 6,
      "L-confirmation": 7,
      "U-confirmation": 8,
      "B-downtime_tolerance": 9,
      "I-downtime_tolerance": 10,
      "L-downtime_tolerance": 11,
      "U-downtime_tolerance": 12,
      "B-feature_type": 13,
      "I-feature_type": 14,
      "L-feature_type": 15,
      "U-feature_type": 16,
      "B-relationship_type": 17,
      "I-relationship_type": 18,
      "L-relationship_type": 19,
      "U-relationship_type": 20,
      "O": 0
    },
    "num_tags": 21
  }
]